click_loglevel/__init__.py
click_loglevel/py.typed
click_loglevel-0.6.1.dist-info/METADATA
click_loglevel-0.6.1.dist-info/WHEEL
click_loglevel-0.6.1.dist-info/licenses/LICENSE
click_loglevel-0.6.1.dist-info/RECORD
