Metadata-Version: 2.4
Name: click-loglevel
Version: 0.6.1
Summary: Log level parameter type for Click
Project-URL: Source Code, https://github.com/jwodder/click-loglevel
Project-URL: Bug Tracker, https://github.com/jwodder/click-loglevel/issues
Author-email: John Thorvald Wodder II <click-loglevel@varonathe.org>
License-Expression: MIT
License-File: LICENSE
Keywords: cli option,click,command line interface,log level,log option,logging,option parsing
Classifier: Environment :: Console
Classifier: Intended Audience :: Developers
Classifier: Programming Language :: Python :: 3
Classifier: Programming Language :: Python :: 3 :: Only
Classifier: Programming Language :: Python :: 3.8
Classifier: Programming Language :: Python :: 3.9
Classifier: Programming Language :: Python :: 3.10
Classifier: Programming Language :: Python :: 3.11
Classifier: Programming Language :: Python :: 3.12
Classifier: Programming Language :: Python :: 3.13
Classifier: Programming Language :: Python :: Implementation :: CPython
Classifier: Programming Language :: Python :: Implementation :: PyPy
Classifier: Topic :: System :: Logging
Classifier: Typing :: Typed
Requires-Python: >=3.8
Requires-Dist: click>=8.0
